README.md
setup.py
deepquantumtensornetwork/__init__.py
deepquantumtensornetwork.egg-info/PKG-INFO
deepquantumtensornetwork.egg-info/SOURCES.txt
deepquantumtensornetwork.egg-info/dependency_links.txt
deepquantumtensornetwork.egg-info/requires.txt
deepquantumtensornetwork.egg-info/top_level.txt
deepquantumtensornetwork/embeddings/__init__.py
deepquantumtensornetwork/embeddings/qembedding.py
deepquantumtensornetwork/gates/__init__.py
deepquantumtensornetwork/gates/qcircuit.py
deepquantumtensornetwork/gates/qgate.py
deepquantumtensornetwork/gates/qmath.py
deepquantumtensornetwork/gates/qoperator.py
deepquantumtensornetwork/layers/__init__.py
deepquantumtensornetwork/layers/qlayer.py
deepquantumtensornetwork/layers/qlayers.py
deepquantumtensornetwork/nn/__init__.py
deepquantumtensornetwork/nn/modules/__init__.py
deepquantumtensornetwork/nn/modules/qconv.py
deepquantumtensornetwork/nn/modules/qpooling.py
deepquantumtensornetwork/nn/modules/qrnn.py
deepquantumtensornetwork/nn/modules/qtransformer.py